coded_exceptions.py
setup.py
coded_exceptions.egg-info/PKG-INFO
coded_exceptions.egg-info/SOURCES.txt
coded_exceptions.egg-info/dependency_links.txt
coded_exceptions.egg-info/top_level.txt